comun_pgsql.py
comun_pgsql-0.2.dist-info/METADATA
comun_pgsql-0.2.dist-info/WHEEL
comun_pgsql-0.2.dist-info/top_level.txt
comun_pgsql-0.2.dist-info/RECORD
