Metadata-Version: 2.1
Name: comun-pgsql
Version: 0.2
Summary: UNKNOWN
Home-page: UNKNOWN
License: UNKNOWN
Platform: UNKNOWN
Requires-Dist: psycopg[binary]
